minipath/__init__.py
minipath/dcm_tools.py
minipath/debug_tools.py
minipath/minipath.py
minipath-1.0.0.dist-info/licenses/LICENSE
minipath-1.0.0.dist-info/METADATA
minipath-1.0.0.dist-info/WHEEL
minipath-1.0.0.dist-info/top_level.txt
minipath-1.0.0.dist-info/RECORD
