Metadata-Version: 2.4
Name: minipath
Version: 1.0.0
Summary: A tool for processing and analyzing digital pathology images stored in DICOM format.
Author: Steven Hart
Author-email: Hart.Steven@Mayo.edu
License: MIT
Requires-Python: >=3.8
License-File: LICENSE
Requires-Dist: google-auth
Requires-Dist: google-cloud-storage
Requires-Dist: numpy
Requires-Dist: pandas
Requires-Dist: pillow
Requires-Dist: pydicom
Requires-Dist: python-dotenv
Requires-Dist: scikit-learn
Requires-Dist: opencv-python
Requires-Dist: scikit-image
Requires-Dist: tqdm
Dynamic: license-file
